django_mailing-0.3.dist-info/licenses/AUTHORS.txt
django_mailing-0.3.dist-info/licenses/LICENSE.txt
mailing/__init__.py
mailing/mail.py
mailing/models.py
mailing/shortcuts.py
mailing/tasks.py
mailing/views.py
mailing/templates/mailing/base.html
mailing/templates/mailing/base.txt
django_mailing-0.3.dist-info/METADATA
django_mailing-0.3.dist-info/WHEEL
django_mailing-0.3.dist-info/top_level.txt
django_mailing-0.3.dist-info/RECORD
