Metadata-Version: 2.4
Name: django-mailing
Version: 0.3
Summary: A flexible Django app for templated mailings with support for celery queuing, SendGrid and more.
Home-page: http://github.com/JeromeParadis/django-mailing
Author: Jerome Paradis
Author-email: jparadis@paradivision.com
License: GPL-3.0-or-later
Classifier: Development Status :: 4 - Beta
Classifier: Environment :: Web Environment
Classifier: Intended Audience :: Developers
Classifier: License :: OSI Approved :: MIT License
Classifier: Operating System :: OS Independent
Classifier: Programming Language :: Python
Classifier: Framework :: Django
License-File: LICENSE.txt
License-File: AUTHORS.txt
Requires-Dist: Django>=1.4.1
Requires-Dist: redis>=2.4.10
Requires-Dist: celery
Requires-Dist: django-celery
Dynamic: author
Dynamic: author-email
Dynamic: classifier
Dynamic: description
Dynamic: home-page
Dynamic: license
Dynamic: license-file
Dynamic: requires-dist
Dynamic: summary
